propargs/__init__.py
propargs/command_line.py
propargs/constants.py
propargs/data_store.py
propargs/env.py
propargs/exceptions.py
propargs/prop.py
propargs/propargs.py
propargs/property_dict.py
propargs/type.py
propargs/user.py
propargs-0.0.20.dist-info/LICENSE
propargs-0.0.20.dist-info/METADATA
propargs-0.0.20.dist-info/WHEEL
propargs-0.0.20.dist-info/top_level.txt
propargs-0.0.20.dist-info/RECORD
