Metadata-Version: 2.1
Name: propargs
Version: 0.0.20
Summary: A module for systematically organizing user preferences acquired from a database, env vars, a parameter file, or user choices.
Home-page: https://github.com/gcallah/PropArgs
Author: Nathan Conroy, Gene Callahan
Author-email: nathanconroydev@gmail.com
License: UNKNOWN
Platform: UNKNOWN
Classifier: Programming Language :: Python :: 3
Classifier: License :: OSI Approved :: GNU General Public License v3 (GPLv3)
Classifier: Operating System :: OS Independent
